{
    "sequencers": [
        {
            "brightness": 1.0,
            "color_blend": 1.0,
            "color_increase": 0.11699999868869781,
            "color_threshold": 0.0,
            "direction": false,
            "energy_velocity": false,
            "fade_blend": 0.014999999664723873,
            "initial_snake_velocity": 3.819999933242798,
            "max_snakes": 53,
            "method": "onset",
            "min_delay_frames": 8,
            "mirror": false,
            "skewness_color_modifier": 0.593999981880188,
            "snake_length": 11,
            "trigger_threshold": 0.5860000252723694,
            "type": "snakes",
            "velocity_decay": 0.003000000026077032,
            "velocity_threshold": 0.0
        },
        {
            "brightness": 1.0,
            "color_blend": 1.0,
            "color_increase": 1.0369999408721924,
            "color_threshold": 0.0,
            "direction": true,
            "energy_velocity": false,
            "fade_blend": 0.5120000243186951,
            "initial_snake_velocity": 2.1429998874664307,
            "max_snakes": 100,
            "method": "kick_normalized",
            "min_delay_frames": 20,
            "mirror": true,
            "skewness_color_modifier": 0.0,
            "snake_length": 5,
            "trigger_threshold": 0.9950000047683716,
            "type": "snakes",
            "velocity_decay": 0.0,
            "velocity_threshold": 0.0
        },
        {
            "brightness": 1.0,
            "color_blend": 1.0,
            "color_increase": 1.0369999408721924,
            "color_threshold": 0.0,
            "direction": true,
            "energy_velocity": false,
            "fade_blend": 0.5120000243186951,
            "initial_snake_velocity": 2.1429998874664307,
            "max_snakes": 100,
            "method": "kick_normalized",
            "min_delay_frames": 20,
            "mirror": true,
            "skewness_color_modifier": 0.0,
            "snake_length": 5,
            "trigger_threshold": 0.9950000047683716,
            "type": "snakes",
            "velocity_decay": 0.0,
            "velocity_threshold": 0.0
        },
        {
            "brightness": 1.0,
            "color_blend": 1.0,
            "color_increase": 1.0369999408721924,
            "color_threshold": 0.0,
            "direction": true,
            "energy_velocity": false,
            "fade_blend": 0.5120000243186951,
            "initial_snake_velocity": 2.1429998874664307,
            "max_snakes": 100,
            "method": "kick_normalized",
            "min_delay_frames": 20,
            "mirror": true,
            "skewness_color_modifier": 0.0,
            "snake_length": 5,
            "trigger_threshold": 0.9950000047683716,
            "type": "snakes",
            "velocity_decay": 0.0,
            "velocity_threshold": 0.0
        },
        {
            "brightness": 1.0,
            "color_blend": 1.0,
            "color_increase": 1.0369999408721924,
            "color_threshold": 0.0,
            "direction": true,
            "energy_velocity": false,
            "fade_blend": 0.5120000243186951,
            "initial_snake_velocity": 2.1429998874664307,
            "max_snakes": 100,
            "method": "kick_normalized",
            "min_delay_frames": 20,
            "mirror": true,
            "skewness_color_modifier": 0.0,
            "snake_length": 5,
            "trigger_threshold": 0.9950000047683716,
            "type": "snakes",
            "velocity_decay": 0.0,
            "velocity_threshold": 0.0
        },
        {
            "brightness": 1.0,
            "color_blend": 1.0,
            "color_increase": 1.0369999408721924,
            "color_threshold": 0.0,
            "direction": true,
            "energy_velocity": false,
            "fade_blend": 0.5120000243186951,
            "initial_snake_velocity": 2.1429998874664307,
            "max_snakes": 100,
            "method": "kick_normalized",
            "min_delay_frames": 20,
            "mirror": true,
            "skewness_color_modifier": 0.0,
            "snake_length": 5,
            "trigger_threshold": 0.9950000047683716,
            "type": "snakes",
            "velocity_decay": 0.0,
            "velocity_threshold": 0.0
        }
    ]
}